pysaql/__init__.py
pysaql/aggregation.py
pysaql/date_.py
pysaql/enums.py
pysaql/expression.py
pysaql/function.py
pysaql/py.typed
pysaql/scalar.py
pysaql/stream.py
pysaql/util.py
pysaql-0.12.0.dist-info/LICENSE.md
pysaql-0.12.0.dist-info/WHEEL
pysaql-0.12.0.dist-info/METADATA
pysaql-0.12.0.dist-info/RECORD
