Metadata-Version: 2.1
Name: pysaql
Version: 0.12.0
Summary: Python SAQL query builder
Home-page: https://github.com/NarrativeScience/pysaql
License: BSD-3-Clause
Author: Jonathan Drake
Author-email: jon.drake@salesforce.com
Requires-Python: >=3.9,<4.0
Classifier: License :: OSI Approved :: BSD License
Classifier: Programming Language :: Python :: 3
Classifier: Programming Language :: Python :: 3.10
Classifier: Programming Language :: Python :: 3.9
Project-URL: Repository, https://github.com/NarrativeScience/pysaql
